ib_message_server-0.1.0.data/scripts/server_run
server/__init__.py
server/common/__init__.py
server/common/decors.py
server/common/errors.py
server/common/settings.py
server/common/utils.py
server/logs/__init__.py
server/logs/conf_server_log.py
server/server/__init__.py
server/server/core.py
server/server/metaclasses.py
server/server/server_db.py
server/server/server_gui.py
server/unit_tests/__init__.py
server/unit_tests/test_client.py
server/unit_tests/test_server.py
server/unit_tests/test_utils.py
server/unit_tests/test_utils2.py
ib_message_server-0.1.0.dist-info/METADATA
ib_message_server-0.1.0.dist-info/WHEEL
ib_message_server-0.1.0.dist-info/top_level.txt
ib_message_server-0.1.0.dist-info/RECORD
