Metadata-Version: 2.1
Name: ib-message-server
Version: 0.1.0
Summary: Server part of Server to client messanger
Home-page: https://pypi.org/project/ib-message-server/
Author: Igor Burakov
Author-email: iburako8@yandex.ru
License: UNKNOWN
Platform: UNKNOWN
Requires-Dist: PyQt5
Requires-Dist: sqlalchemy
Requires-Dist: pycryptodome
Requires-Dist: pycryptodomex
